{
  "minecraft:recipes/tools/fishing_rod": {
    "criteria": {
      "has_string": "2022-08-24 19:24:11 +0200"
    },
    "done": true
  },
  "minecraft:recipes/building_blocks/polished_blackstone_brick_stairs_from_polished_blackstone_stonecutting": {
    "criteria": {
      "has_polished_blackstone": "2022-08-25 19:07:52 +0200"
    },
    "done": true
  },
  "minecraft:recipes/redstone/lever": {
    "criteria": {
      "has_cobblestone": "2022-08-25 18:43:54 +0200"
    },
    "done": true
  },
  "minecraft:recipes/building_blocks/cobblestone_stairs_from_cobblestone_stonecutting": {
    "criteria": {
      "has_cobblestone": "2022-08-25 18:43:54 +0200"
    },
    "done": true
  },
  "minecraft:recipes/combat/iron_sword": {
    "criteria": {
      "has_iron_ingot": "2022-08-25 20:09:18 +0200"
    },
    "done": true
  },
  "minecraft:recipes/building_blocks/stone_bricks": {
    "criteria": {
      "has_stone": "2022-08-25 22:15:30 +0200"
    },
    "done": true
  },
  "minecraft:recipes/building_blocks/nether_brick_slab": {
    "criteria": {
      "has_nether_brick": "2022-08-25 19:08:01 +0200"
    },
    "done": true
  },
  "minecraft:recipes/tools/iron_pickaxe": {
    "criteria": {
      "has_iron_ingot": "2022-08-25 20:09:18 +0200"
    },
    "done": true
  },
  "minecraft:nether/root": {
    "criteria": {
      "entered_nether": "2022-08-24 16:46:05 +0200"
    },
    "done": true
  },
  "minecraft:recipes/building_blocks/crimson_hyphae": {
    "criteria": {
      "has_log": "2022-08-24 17:15:10 +0200"
    },
    "done": true
  },
  "minecraft:recipes/decorations/crafting_table": {
    "criteria": {
      "has_planks": "2022-08-24 17:41:07 +0200"
    },
    "done": true
  },
  "minecraft:recipes/decorations/campfire": {
    "criteria": {
      "has_stick": "2022-08-24 19:24:11 +0200"
    },
    "done": true
  },
  "minecraft:recipes/tools/golden_hoe": {
    "criteria": {
      "has_gold_ingot": "2022-08-24 17:55:16 +0200"
    },
    "done": true
  },
  "minecraft:recipes/building_blocks/smooth_stone": {
    "criteria": {
      "has_the_recipe": "2022-08-25 22:14:27 +0200"
    },
    "done": true
  },
  "minecraft:recipes/decorations/blast_furnace": {
    "criteria": {
      "has_smooth_stone": "2022-08-25 22:15:30 +0200"
    },
    "done": true
  },
  "minecraft:recipes/decorations/ladder": {
    "criteria": {
      "has_stick": "2022-08-24 19:24:11 +0200"
    },
    "done": true
  },
  "minecraft:recipes/misc/iron_nugget": {
    "criteria": {
      "has_iron_ingot": "2022-08-25 20:09:18 +0200"
    },
    "done": true
  },
  "minecraft:recipes/combat/golden_sword": {
    "criteria": {
      "has_gold_ingot": "2022-08-24 17:55:16 +0200"
    },
    "done": true
  },
  "minecraft:recipes/decorations/chest": {
    "criteria": {
      "has_lots_of_items": "2022-08-24 19:40:32 +0200"
    },
    "done": true
  },
  "minecraft:recipes/decorations/nether_brick_wall": {
    "criteria": {
      "has_nether_bricks": "2022-08-25 19:08:01 +0200"
    },
    "done": true
  },
  "minecraft:recipes/building_blocks/stone_slab_from_stone_stonecutting": {
    "criteria": {
      "has_stone": "2022-08-25 22:15:30 +0200"
    },
    "done": true
  },
  "minecraft:recipes/building_blocks/chiseled_stone_bricks_stone_from_stonecutting": {
    "criteria": {
      "has_stone": "2022-08-25 22:15:30 +0200"
    },
    "done": true
  },
  "minecraft:recipes/tools/wooden_shovel": {
    "criteria": {
      "has_stick": "2022-08-24 19:24:11 +0200"
    },
    "done": true
  },
  "minecraft:recipes/decorations/torch": {
    "criteria": {
      "has_stone_pickaxe": "2022-08-25 18:45:18 +0200"
    },
    "done": true
  },
  "minecraft:recipes/misc/white_dye": {
    "criteria": {
      "has_bone_meal": "2022-08-24 17:02:38 +0200"
    },
    "done": true
  },
  "minecraft:recipes/tools/shears": {
    "criteria": {
      "has_iron_ingot": "2022-08-25 20:09:18 +0200"
    },
    "done": true
  },
  "minecraft:recipes/misc/stick": {
    "criteria": {
      "has_planks": "2022-08-24 17:41:07 +0200"
    },
    "done": true
  },
  "minecraft:recipes/redstone/crimson_pressure_plate": {
    "criteria": {
      "has_planks": "2022-08-24 17:41:07 +0200"
    },
    "done": true
  },
  "minecraft:recipes/redstone/redstone_lamp": {
    "criteria": {
      "has_glowstone": "2022-08-25 20:03:25 +0200"
    },
    "done": true
  },
  "minecraft:recipes/building_blocks/stone_brick_slab_from_stone_stonecutting": {
    "criteria": {
      "has_stone": "2022-08-25 22:15:30 +0200"
    },
    "done": true
  },
  "minecraft:recipes/transportation/spruce_boat": {
    "criteria": {
      "in_water": "2022-08-25 18:26:55 +0200"
    },
    "done": true
  },
  "minecraft:recipes/redstone/polished_blackstone_button": {
    "criteria": {
      "has_polished_blackstone": "2022-08-25 19:07:52 +0200"
    },
    "done": true
  },
  "minecraft:recipes/decorations/crimson_fence": {
    "criteria": {
      "has_planks": "2022-08-24 17:41:07 +0200"
    },
    "done": true
  },
  "minecraft:recipes/redstone/dispenser": {
    "criteria": {
      "has_bow": "2022-08-24 19:24:19 +0200"
    },
    "done": true
  },
  "minecraft:recipes/misc/gold_nugget": {
    "criteria": {
      "has_gold_ingot": "2022-08-24 17:55:16 +0200"
    },
    "done": true
  },
  "minecraft:recipes/combat/iron_leggings": {
    "criteria": {
      "has_iron_ingot": "2022-08-25 20:09:18 +0200"
    },
    "done": true
  },
  "minecraft:recipes/brewing/golden_carrot": {
    "criteria": {
      "has_gold_nugget": "2022-08-24 17:55:17 +0200"
    },
    "done": true
  },
  "minecraft:recipes/tools/wooden_hoe": {
    "criteria": {
      "has_stick": "2022-08-24 19:24:11 +0200"
    },
    "done": true
  },
  "minecraft:recipes/combat/shield": {
    "criteria": {
      "has_iron_ingot": "2022-08-25 20:09:18 +0200"
    },
    "done": true
  },
  "minecraft:recipes/building_blocks/cobblestone_slab": {
    "criteria": {
      "has_cobblestone": "2022-08-25 18:43:54 +0200"
    },
    "done": true
  },
  "minecraft:recipes/food/cooked_cod": {
    "criteria": {
      "has_cod": "2022-08-25 18:28:53 +0200"
    },
    "done": true
  },
  "minecraft:recipes/building_blocks/polished_blackstone_from_blackstone_stonecutting": {
    "criteria": {
      "has_blackstone": "2022-08-25 19:01:38 +0200"
    },
    "done": true
  },
  "minecraft:recipes/misc/bucket": {
    "criteria": {
      "has_iron_ingot": "2022-08-25 20:09:18 +0200"
    },
    "done": true
  },
  "minecraft:recipes/redstone/trapped_chest": {
    "criteria": {
      "has_tripwire_hook": "2022-08-25 18:28:18 +0200"
    },
    "done": true
  },
  "minecraft:recipes/building_blocks/cobblestone_stairs": {
    "criteria": {
      "has_cobblestone": "2022-08-25 18:43:54 +0200"
    },
    "done": true
  },
  "minecraft:recipes/redstone/hopper": {
    "criteria": {
      "has_iron_ingot": "2022-08-25 20:09:18 +0200"
    },
    "done": true
  },
  "minecraft:recipes/decorations/polished_blackstone_wall_from_polished_blackstone_stonecutting": {
    "criteria": {
      "has_polished_blackstone": "2022-08-25 19:07:52 +0200"
    },
    "done": true
  },
  "minecraft:recipes/redstone/note_block": {
    "criteria": {
      "has_redstone": "2022-08-25 19:30:38 +0200"
    },
    "done": true
  },
  "minecraft:recipes/building_blocks/polished_blackstone_stairs_from_blackstone_stonecutting": {
    "criteria": {
      "has_blackstone": "2022-08-25 19:01:38 +0200"
    },
    "done": true
  },
  "minecraft:recipes/tools/golden_shovel": {
    "criteria": {
      "has_gold_ingot": "2022-08-24 17:55:16 +0200"
    },
    "done": true
  },
  "minecraft:recipes/combat/iron_helmet": {
    "criteria": {
      "has_iron_ingot": "2022-08-25 20:09:18 +0200"
    },
    "done": true
  },
  "minecraft:recipes/combat/bow": {
    "criteria": {
      "has_string": "2022-08-24 19:24:11 +0200"
    },
    "done": true
  },
  "minecraft:recipes/food/cooked_chicken_from_smoking": {
    "criteria": {
      "has_chicken": "2022-08-24 19:40:32 +0200"
    },
    "done": true
  },
  "minecraft:recipes/redstone/tnt": {
    "criteria": {
      "has_gunpowder": "2022-08-25 19:31:21 +0200"
    },
    "done": true
  },
  "minecraft:recipes/building_blocks/stone_stairs_from_stone_stonecutting": {
    "criteria": {
      "has_stone": "2022-08-25 22:15:30 +0200"
    },
    "done": true
  },
  "minecraft:recipes/building_blocks/smooth_stone_slab": {
    "criteria": {
      "has_smooth_stone": "2022-08-25 22:15:30 +0200"
    },
    "done": true
  },
  "minecraft:recipes/decorations/iron_bars": {
    "criteria": {
      "has_iron_ingot": "2022-08-25 20:09:18 +0200"
    },
    "done": true
  },
  "minecraft:recipes/redstone/crimson_button": {
    "criteria": {
      "has_planks": "2022-08-24 17:41:07 +0200"
    },
    "done": true
  },
  "minecraft:recipes/building_blocks/gold_block": {
    "criteria": {
      "has_gold_ingot": "2022-08-24 17:55:16 +0200"
    },
    "done": true
  },
  "minecraft:story/mine_stone": {
    "criteria": {
      "get_stone": "2022-08-25 18:43:54 +0200"
    },
    "done": true
  },
  "minecraft:recipes/redstone/target": {
    "criteria": {
      "has_redstone": "2022-08-25 19:30:38 +0200"
    },
    "done": true
  },
  "minecraft:recipes/decorations/furnace": {
    "criteria": {
      "has_cobblestone": "2022-08-25 18:43:54 +0200"
    },
    "done": true
  },
  "minecraft:recipes/transportation/minecart": {
    "criteria": {
      "has_iron_ingot": "2022-08-25 20:09:18 +0200"
    },
    "done": true
  },
  "minecraft:recipes/brewing/cauldron": {
    "criteria": {
      "has_water_bucket": "2022-08-25 19:18:40 +0200"
    },
    "done": true
  },
  "minecraft:recipes/redstone/crimson_door": {
    "criteria": {
      "has_planks": "2022-08-24 17:41:07 +0200"
    },
    "done": true
  },
  "minecraft:recipes/tools/wooden_pickaxe": {
    "criteria": {
      "has_stick": "2022-08-24 19:24:11 +0200"
    },
    "done": true
  },
  "minecraft:recipes/tools/iron_hoe": {
    "criteria": {
      "has_iron_ingot": "2022-08-25 20:09:18 +0200"
    },
    "done": true
  },
  "minecraft:recipes/building_blocks/cobblestone_slab_from_cobblestone_stonecutting": {
    "criteria": {
      "has_cobblestone": "2022-08-25 18:43:54 +0200"
    },
    "done": true
  },
  "minecraft:recipes/redstone/redstone_torch": {
    "criteria": {
      "has_redstone": "2022-08-25 19:30:38 +0200"
    },
    "done": true
  },
  "minecraft:recipes/transportation/birch_boat": {
    "criteria": {
      "in_water": "2022-08-25 18:26:55 +0200"
    },
    "done": true
  },
  "minecraft:recipes/food/golden_apple": {
    "criteria": {
      "has_gold_ingot": "2022-08-24 17:55:16 +0200"
    },
    "done": true
  },
  "minecraft:recipes/transportation/acacia_boat": {
    "criteria": {
      "in_water": "2022-08-25 18:26:55 +0200"
    },
    "done": true
  },
  "minecraft:recipes/tools/iron_shovel": {
    "criteria": {
      "has_iron_ingot": "2022-08-25 20:09:18 +0200"
    },
    "done": true
  },
  "minecraft:recipes/redstone/iron_trapdoor": {
    "criteria": {
      "has_iron_ingot": "2022-08-25 20:09:18 +0200"
    },
    "done": true
  },
  "minecraft:recipes/building_blocks/chiseled_polished_blackstone_from_polished_blackstone_stonecutting": {
    "criteria": {
      "has_polished_blackstone": "2022-08-25 19:07:52 +0200"
    },
    "done": true
  },
  "minecraft:recipes/building_blocks/polished_blackstone": {
    "criteria": {
      "has_blackstone": "2022-08-25 19:01:38 +0200"
    },
    "done": true
  },
  "minecraft:adventure/root": {
    "criteria": {
      "killed_something": "2022-08-24 17:10:59 +0200"
    },
    "done": true
  },
  "minecraft:recipes/food/cooked_salmon_from_campfire_cooking": {
    "criteria": {
      "has_salmon": "2022-08-25 18:32:56 +0200"
    },
    "done": true
  },
  "minecraft:recipes/building_blocks/stone_brick_stairs_from_stone_stonecutting": {
    "criteria": {
      "has_stone": "2022-08-25 22:15:30 +0200"
    },
    "done": true
  },
  "minecraft:recipes/redstone/crimson_trapdoor": {
    "criteria": {
      "has_planks": "2022-08-24 17:41:07 +0200"
    },
    "done": true
  },
  "minecraft:recipes/building_blocks/white_wool_from_string": {
    "criteria": {
      "has_string": "2022-08-24 19:24:11 +0200"
    },
    "done": true
  },
  "minecraft:recipes/tools/stone_hoe": {
    "criteria": {
      "has_cobblestone": "2022-08-25 18:43:54 +0200"
    },
    "done": true
  },
  "minecraft:recipes/tools/clock": {
    "criteria": {
      "has_redstone": "2022-08-25 19:30:38 +0200"
    },
    "done": true
  },
  "minecraft:recipes/combat/spectral_arrow": {
    "criteria": {
      "has_glowstone_dust": "2022-08-25 19:31:56 +0200"
    },
    "done": true
  },
  "minecraft:adventure/kill_all_mobs": {
    "criteria": {
      "minecraft:skeleton": "2022-08-25 20:03:07 +0200",
      "minecraft:magma_cube": "2022-08-24 19:19:41 +0200",
      "minecraft:spider": "2022-08-25 20:25:09 +0200",
      "minecraft:zombified_piglin": "2022-08-24 17:25:14 +0200",
      "minecraft:witch": "2022-08-25 19:30:12 +0200",
      "minecraft:piglin": "2022-08-24 19:22:27 +0200"
    },
    "done": false
  },
  "minecraft:story/enter_the_nether": {
    "criteria": {
      "entered_nether": "2022-08-24 16:46:05 +0200"
    },
    "done": true
  },
  "minecraft:recipes/redstone/redstone_block": {
    "criteria": {
      "has_redstone": "2022-08-25 19:30:38 +0200"
    },
    "done": true
  },
  "minecraft:recipes/decorations/crimson_sign": {
    "criteria": {
      "has_crimson_planks": "2022-08-24 17:41:07 +0200"
    },
    "done": true
  },
  "minecraft:recipes/food/cooked_chicken_from_campfire_cooking": {
    "criteria": {
      "has_chicken": "2022-08-24 19:40:32 +0200"
    },
    "done": true
  },
  "minecraft:recipes/building_blocks/cracked_nether_bricks": {
    "criteria": {
      "has_nether_bricks": "2022-08-25 19:08:01 +0200"
    },
    "done": true
  },
  "minecraft:recipes/building_blocks/polished_blackstone_brick_stairs_from_blackstone_stonecutting": {
    "criteria": {
      "has_blackstone": "2022-08-25 19:01:38 +0200"
    },
    "done": true
  },
  "minecraft:recipes/misc/gold_ingot_from_nuggets": {
    "criteria": {
      "has_gold_nugget": "2022-08-24 17:55:17 +0200"
    },
    "done": true
  },
  "minecraft:recipes/decorations/chain": {
    "criteria": {
      "has_iron_ingot": "2022-08-25 20:09:18 +0200"
    },
    "done": true
  },
  "minecraft:story/upgrade_tools": {
    "criteria": {
      "stone_pickaxe": "2022-08-25 18:45:18 +0200"
    },
    "done": true
  },
  "minecraft:recipes/redstone/polished_blackstone_pressure_plate": {
    "criteria": {
      "has_polished_blackstone": "2022-08-25 19:07:52 +0200"
    },
    "done": true
  },
  "minecraft:recipes/decorations/nether_brick_wall_from_nether_bricks_stonecutting": {
    "criteria": {
      "has_nether_bricks": "2022-08-25 19:08:01 +0200"
    },
    "done": true
  },
  "minecraft:recipes/transportation/oak_boat": {
    "criteria": {
      "in_water": "2022-08-25 18:26:55 +0200"
    },
    "done": true
  },
  "minecraft:recipes/building_blocks/polished_blackstone_bricks_from_blackstone_stonecutting": {
    "criteria": {
      "has_blackstone": "2022-08-25 19:01:38 +0200"
    },
    "done": true
  },
  "minecraft:recipes/food/cooked_cod_from_campfire_cooking": {
    "criteria": {
      "has_cod": "2022-08-25 18:28:53 +0200"
    },
    "done": true
  },
  "minecraft:recipes/combat/golden_boots": {
    "criteria": {
      "has_gold_ingot": "2022-08-24 17:55:16 +0200"
    },
    "done": true
  },
  "minecraft:recipes/building_blocks/smooth_stone_slab_from_smooth_stone_stonecutting": {
    "criteria": {
      "has_smooth_stone": "2022-08-25 22:15:30 +0200"
    },
    "done": true
  },
  "minecraft:recipes/building_blocks/chiseled_polished_blackstone": {
    "criteria": {
      "has_polished_blackstone": "2022-08-25 19:07:52 +0200"
    },
    "done": true
  },
  "minecraft:recipes/tools/wooden_axe": {
    "criteria": {
      "has_stick": "2022-08-24 19:24:11 +0200"
    },
    "done": true
  },
  "minecraft:recipes/building_blocks/stone_bricks_from_stone_stonecutting": {
    "criteria": {
      "has_stone": "2022-08-25 22:15:30 +0200"
    },
    "done": true
  },
  "minecraft:recipes/building_blocks/chiseled_nether_bricks_from_nether_bricks_stonecutting": {
    "criteria": {
      "has_nether_bricks": "2022-08-25 19:08:01 +0200"
    },
    "done": true
  },
  "minecraft:recipes/combat/golden_chestplate": {
    "criteria": {
      "has_gold_ingot": "2022-08-24 17:55:16 +0200"
    },
    "done": true
  },
  "minecraft:recipes/food/cooked_salmon_from_smoking": {
    "criteria": {
      "has_salmon": "2022-08-25 18:32:56 +0200"
    },
    "done": true
  },
  "minecraft:recipes/decorations/loom": {
    "criteria": {
      "has_string": "2022-08-24 19:24:11 +0200"
    },
    "done": true
  },
  "minecraft:recipes/building_blocks/polished_blackstone_brick_slab_from_polished_blackstone_stonecutting": {
    "criteria": {
      "has_polished_blackstone": "2022-08-25 19:07:52 +0200"
    },
    "done": true
  },
  "minecraft:recipes/building_blocks/crimson_slab": {
    "criteria": {
      "has_planks": "2022-08-24 17:41:07 +0200"
    },
    "done": true
  },
  "minecraft:recipes/building_blocks/polished_blackstone_bricks": {
    "criteria": {
      "has_polished_blackstone": "2022-08-25 19:07:52 +0200"
    },
    "done": true
  },
  "minecraft:recipes/building_blocks/nether_brick_stairs_from_nether_bricks_stonecutting": {
    "criteria": {
      "has_nether_bricks": "2022-08-25 19:08:01 +0200"
    },
    "done": true
  },
  "minecraft:recipes/building_blocks/iron_block": {
    "criteria": {
      "has_iron_ingot": "2022-08-25 20:09:18 +0200"
    },
    "done": true
  },
  "minecraft:recipes/decorations/blackstone_wall_from_blackstone_stonecutting": {
    "criteria": {
      "has_blackstone": "2022-08-25 19:01:38 +0200"
    },
    "done": true
  },
  "minecraft:recipes/building_blocks/crimson_stairs": {
    "criteria": {
      "has_planks": "2022-08-24 17:41:07 +0200"
    },
    "done": true
  },
  "minecraft:recipes/redstone/crimson_fence_gate": {
    "criteria": {
      "has_planks": "2022-08-24 17:41:07 +0200"
    },
    "done": true
  },
  "minecraft:recipes/building_blocks/blackstone_stairs": {
    "criteria": {
      "has_blackstone": "2022-08-25 19:01:38 +0200"
    },
    "done": true
  },
  "minecraft:recipes/combat/arrow": {
    "criteria": {
      "has_feather": "2022-08-24 19:40:32 +0200"
    },
    "done": true
  },
  "minecraft:recipes/building_blocks/stone_slab": {
    "criteria": {
      "has_stone": "2022-08-25 22:15:30 +0200"
    },
    "done": true
  },
  "minecraft:recipes/redstone/light_weighted_pressure_plate": {
    "criteria": {
      "has_gold_ingot": "2022-08-24 17:55:16 +0200"
    },
    "done": true
  },
  "minecraft:recipes/misc/gold_nugget_from_blasting": {
    "criteria": {
      "has_golden_sword": "2022-08-24 19:15:18 +0200"
    },
    "done": true
  },
  "minecraft:recipes/combat/wooden_sword": {
    "criteria": {
      "has_stick": "2022-08-24 19:24:11 +0200"
    },
    "done": true
  },
  "minecraft:recipes/tools/stone_shovel": {
    "criteria": {
      "has_cobblestone": "2022-08-25 18:43:54 +0200"
    },
    "done": true
  },
  "minecraft:recipes/building_blocks/blackstone_slab_from_blackstone_stonecutting": {
    "criteria": {
      "has_blackstone": "2022-08-25 19:01:38 +0200"
    },
    "done": true
  },
  "minecraft:recipes/decorations/polished_blackstone_wall_from_blackstone_stonecutting": {
    "criteria": {
      "has_blackstone": "2022-08-25 19:01:38 +0200"
    },
    "done": true
  },
  "minecraft:recipes/tools/golden_axe": {
    "criteria": {
      "has_gold_ingot": "2022-08-24 17:55:16 +0200"
    },
    "done": true
  },
  "minecraft:recipes/tools/iron_axe": {
    "criteria": {
      "has_iron_ingot": "2022-08-25 20:09:18 +0200"
    },
    "done": true
  },
  "minecraft:recipes/building_blocks/glowstone": {
    "criteria": {
      "has_glowstone_dust": "2022-08-25 19:31:56 +0200"
    },
    "done": true
  },
  "minecraft:recipes/building_blocks/crimson_planks": {
    "criteria": {
      "has_logs": "2022-08-24 17:15:10 +0200"
    },
    "done": true
  },
  "minecraft:recipes/combat/golden_helmet": {
    "criteria": {
      "has_gold_ingot": "2022-08-24 17:55:16 +0200"
    },
    "done": true
  },
  "minecraft:recipes/redstone/tripwire_hook": {
    "criteria": {
      "has_string": "2022-08-24 19:24:11 +0200"
    },
    "done": true
  },
  "minecraft:recipes/combat/iron_boots": {
    "criteria": {
      "has_iron_ingot": "2022-08-25 20:09:18 +0200"
    },
    "done": true
  },
  "minecraft:recipes/misc/bone_meal": {
    "criteria": {
      "has_bone": "2022-08-25 18:37:07 +0200"
    },
    "done": true
  },
  "minecraft:recipes/decorations/blackstone_wall": {
    "criteria": {
      "has_blackstone": "2022-08-25 19:01:38 +0200"
    },
    "done": true
  },
  "minecraft:recipes/building_blocks/polished_blackstone_stairs_from_polished_blackstone_stonecutting": {
    "criteria": {
      "has_polished_blackstone": "2022-08-25 19:07:52 +0200"
    },
    "done": true
  },
  "minecraft:recipes/food/cooked_salmon": {
    "criteria": {
      "has_salmon": "2022-08-25 18:32:56 +0200"
    },
    "done": true
  },
  "minecraft:recipes/decorations/polished_blackstone_brick_wall_from_blackstone_stonecutting": {
    "criteria": {
      "has_blackstone": "2022-08-25 19:01:38 +0200"
    },
    "done": true
  },
  "minecraft:recipes/building_blocks/blackstone_slab": {
    "criteria": {
      "has_blackstone": "2022-08-25 19:01:38 +0200"
    },
    "done": true
  },
  "minecraft:recipes/redstone/stone_button": {
    "criteria": {
      "has_stone": "2022-08-25 22:15:30 +0200"
    },
    "done": true
  },
  "minecraft:recipes/combat/crossbow": {
    "criteria": {
      "has_stick": "2022-08-24 19:24:11 +0200"
    },
    "done": true
  },
  "minecraft:recipes/redstone/dropper": {
    "criteria": {
      "has_redstone": "2022-08-25 19:30:38 +0200"
    },
    "done": true
  },
  "minecraft:recipes/combat/iron_chestplate": {
    "criteria": {
      "has_iron_ingot": "2022-08-25 20:09:18 +0200"
    },
    "done": true
  },
  "minecraft:recipes/building_blocks/polished_blackstone_slab_from_blackstone_stonecutting": {
    "criteria": {
      "has_blackstone": "2022-08-25 19:01:38 +0200"
    },
    "done": true
  },
  "minecraft:recipes/building_blocks/chiseled_nether_bricks": {
    "criteria": {
      "has_nether_bricks": "2022-08-25 19:08:01 +0200"
    },
    "done": true
  },
  "minecraft:recipes/building_blocks/nether_brick_slab_from_nether_bricks_stonecutting": {
    "criteria": {
      "has_nether_bricks": "2022-08-25 19:08:01 +0200"
    },
    "done": true
  },
  "minecraft:recipes/tools/compass": {
    "criteria": {
      "has_redstone": "2022-08-25 19:30:38 +0200"
    },
    "done": true
  },
  "minecraft:recipes/redstone/repeater": {
    "criteria": {
      "has_redstone_torch": "2022-08-25 20:10:14 +0200"
    },
    "done": true
  },
  "minecraft:adventure/kill_a_mob": {
    "criteria": {
      "minecraft:zombified_piglin": "2022-08-24 17:25:14 +0200"
    },
    "done": true
  },
  "minecraft:recipes/tools/golden_pickaxe": {
    "criteria": {
      "has_gold_ingot": "2022-08-24 17:55:16 +0200"
    },
    "done": true
  },
  "minecraft:adventure/ol_betsy": {
    "criteria": {
      "shot_crossbow": "2022-08-24 19:26:31 +0200"
    },
    "done": true
  },
  "minecraft:recipes/building_blocks/stone": {
    "criteria": {
      "has_cobblestone": "2022-08-25 18:43:54 +0200"
    },
    "done": true
  },
  "minecraft:recipes/building_blocks/polished_blackstone_slab_from_polished_blackstone_stonecutting": {
    "criteria": {
      "has_polished_blackstone": "2022-08-25 19:07:52 +0200"
    },
    "done": true
  },
  "minecraft:recipes/decorations/stonecutter": {
    "criteria": {
      "has_stone": "2022-08-25 22:15:30 +0200"
    },
    "done": true
  },
  "minecraft:adventure/adventuring_time": {
    "criteria": {
      "minecraft:taiga": "2022-08-24 16:45:11 +0200",
      "minecraft:giant_tree_taiga": "2022-08-24 20:10:26 +0200",
      "minecraft:swamp": "2022-08-25 18:51:22 +0200"
    },
    "done": false
  },
  "minecraft:recipes/redstone/iron_door": {
    "criteria": {
      "has_iron_ingot": "2022-08-25 20:09:18 +0200"
    },
    "done": true
  },
  "minecraft:recipes/decorations/composter": {
    "criteria": {
      "has_wood_slab": "2022-08-24 17:05:32 +0200"
    },
    "done": true
  },
  "minecraft:recipes/decorations/nether_brick_fence": {
    "criteria": {
      "has_nether_brick": "2022-08-25 19:08:01 +0200"
    },
    "done": true
  },
  "minecraft:recipes/building_blocks/chiseled_polished_blackstone_from_blackstone_stonecutting": {
    "criteria": {
      "has_blackstone": "2022-08-25 19:01:38 +0200"
    },
    "done": true
  },
  "minecraft:recipes/combat/stone_sword": {
    "criteria": {
      "has_cobblestone": "2022-08-25 18:43:54 +0200"
    },
    "done": true
  },
  "minecraft:recipes/decorations/barrel": {
    "criteria": {
      "has_wood_slab": "2022-08-24 17:05:32 +0200"
    },
    "done": true
  },
  "minecraft:recipes/decorations/cobblestone_wall": {
    "criteria": {
      "has_cobblestone": "2022-08-25 18:43:54 +0200"
    },
    "done": true
  },
  "minecraft:recipes/brewing/fermented_spider_eye": {
    "criteria": {
      "has_spider_eye": "2022-08-25 19:50:44 +0200"
    },
    "done": true
  },
  "minecraft:recipes/tools/stone_pickaxe": {
    "criteria": {
      "has_cobblestone": "2022-08-25 18:43:54 +0200"
    },
    "done": true
  },
  "minecraft:recipes/decorations/smithing_table": {
    "criteria": {
      "has_iron_ingot": "2022-08-25 20:09:18 +0200"
    },
    "done": true
  },
  "minecraft:recipes/building_blocks/blackstone_stairs_from_blackstone_stonecutting": {
    "criteria": {
      "has_blackstone": "2022-08-25 19:01:38 +0200"
    },
    "done": true
  },
  "minecraft:recipes/redstone/stone_pressure_plate": {
    "criteria": {
      "has_stone": "2022-08-25 22:15:30 +0200"
    },
    "done": true
  },
  "minecraft:recipes/building_blocks/polished_blackstone_slab": {
    "criteria": {
      "has_polished_blackstone": "2022-08-25 19:07:52 +0200"
    },
    "done": true
  },
  "minecraft:recipes/transportation/jungle_boat": {
    "criteria": {
      "in_water": "2022-08-25 18:26:55 +0200"
    },
    "done": true
  },
  "minecraft:adventure/shoot_arrow": {
    "criteria": {
      "shot_arrow": "2022-08-24 19:24:32 +0200"
    },
    "done": true
  },
  "minecraft:recipes/decorations/cobblestone_wall_from_cobblestone_stonecutting": {
    "criteria": {
      "has_cobblestone": "2022-08-25 18:43:54 +0200"
    },
    "done": true
  },
  "minecraft:recipes/decorations/stone_brick_walls_from_stone_stonecutting": {
    "criteria": {
      "has_stone": "2022-08-25 22:15:30 +0200"
    },
    "done": true
  },
  "minecraft:recipes/building_blocks/polished_blackstone_stairs": {
    "criteria": {
      "has_polished_blackstone": "2022-08-25 19:07:52 +0200"
    },
    "done": true
  },
  "minecraft:recipes/decorations/polished_blackstone_wall": {
    "criteria": {
      "has_polished_blackstone": "2022-08-25 19:07:52 +0200"
    },
    "done": true
  },
  "minecraft:recipes/redstone/heavy_weighted_pressure_plate": {
    "criteria": {
      "has_iron_ingot": "2022-08-25 20:09:18 +0200"
    },
    "done": true
  },
  "minecraft:recipes/transportation/dark_oak_boat": {
    "criteria": {
      "in_water": "2022-08-25 18:26:55 +0200"
    },
    "done": true
  },
  "minecraft:husbandry/fishy_business": {
    "criteria": {
      "cod": "2022-08-25 18:28:53 +0200"
    },
    "done": true
  },
  "minecraft:recipes/building_blocks/nether_brick_stairs": {
    "criteria": {
      "has_nether_brick": "2022-08-25 19:08:01 +0200"
    },
    "done": true
  },
  "minecraft:recipes/building_blocks/polished_blackstone_brick_slab_from_blackstone_stonecutting": {
    "criteria": {
      "has_blackstone": "2022-08-25 19:01:38 +0200"
    },
    "done": true
  },
  "minecraft:recipes/combat/golden_leggings": {
    "criteria": {
      "has_gold_ingot": "2022-08-24 17:55:16 +0200"
    },
    "done": true
  },
  "minecraft:recipes/food/cooked_cod_from_smoking": {
    "criteria": {
      "has_cod": "2022-08-25 18:28:53 +0200"
    },
    "done": true
  },
  "minecraft:recipes/redstone/piston": {
    "criteria": {
      "has_redstone": "2022-08-25 19:30:38 +0200"
    },
    "done": true
  },
  "minecraft:recipes/decorations/lantern": {
    "criteria": {
      "has_iron_ingot": "2022-08-25 20:09:18 +0200"
    },
    "done": true
  },
  "minecraft:recipes/building_blocks/stone_stairs": {
    "criteria": {
      "has_stone": "2022-08-25 22:15:30 +0200"
    },
    "done": true
  },
  "minecraft:nether/explore_nether": {
    "criteria": {
      "minecraft:nether_wastes": "2022-08-24 16:46:06 +0200"
    },
    "done": false
  },
  "minecraft:recipes/misc/gold_nugget_from_smelting": {
    "criteria": {
      "has_golden_sword": "2022-08-24 19:15:18 +0200"
    },
    "done": true
  },
  "minecraft:recipes/food/cooked_chicken": {
    "criteria": {
      "has_chicken": "2022-08-24 19:40:32 +0200"
    },
    "done": true
  },
  "minecraft:recipes/decorations/polished_blackstone_brick_wall_from_polished_blackstone_stonecutting": {
    "criteria": {
      "has_polished_blackstone": "2022-08-25 19:07:52 +0200"
    },
    "done": true
  },
  "minecraft:recipes/decorations/soul_campfire": {
    "criteria": {
      "has_stick": "2022-08-24 19:24:11 +0200"
    },
    "done": true
  },
  "minecraft:story/smelt_iron": {
    "criteria": {
      "iron": "2022-08-25 20:09:18 +0200"
    },
    "done": true
  },
  "minecraft:recipes/tools/stone_axe": {
    "criteria": {
      "has_cobblestone": "2022-08-25 18:43:54 +0200"
    },
    "done": true
  },
  "minecraft:recipes/decorations/soul_torch": {
    "criteria": {
      "has_soul_sand": "2022-08-25 19:27:04 +0200"
    },
    "done": true
  },
  "minecraft:recipes/building_blocks/polished_blackstone_bricks_from_polished_blackstone_stonecutting": {
    "criteria": {
      "has_polished_blackstone": "2022-08-25 19:07:52 +0200"
    },
    "done": true
  },
  "minecraft:recipes/building_blocks/bone_block": {
    "criteria": {
      "has_bonemeal": "2022-08-24 17:02:38 +0200"
    },
    "done": true
  },
  "DataVersion": 2584
}